{
    "flagCorrectFalseMShots": true,
    "flagFilterFalseMShots": false,
    "flagDTCor": true,
    "flagWVCalibration": true,
    "flagDepolCali": false,
    "flagUsePreviousDepolCali": false,
    "flagUsePreviousWVconst": true,
    "flagUsePreviousLC": true,
    "flagUseSameRefH": true,
    "MWRFolder": "",
    "dataFileFormat": "(?<year>\\d{4})_(?<month>\\d{2})_(?<day>\\d{2})_\\w*_(?<hour>\\d{2})_(?<minute>\\d{2})_(?<second>\\d{2})\\w*.nc",
    "gdas1Site": "leipzig",
    "AERONETSite": "Leipzig",
    "max_height_bin": 2000,
    "first_range_gate_indx": [1, 1, 1, 1, 1, 1, 1, 1],
    "first_range_gate_height": 39,
    "dtCorModeLabel": ["Polynomial coefficients stores in netcdf file", "nonparalyzable correction", "User defined polynomial cofficients", "No deadtime correction"],
    "dtCorMode": 4,
    "bgCorRangeIndx": [1300, 1800],
    "mask_SNRmin": [1.6, 1, 1, 1.5, 1, 1.5, 0.01, 1],
    "init_depAng": 
    "isFR": [1, 1, 1, 1, 1, 1, 1, 1], 
    "isNR": [0, 0, 0, 0, 0, 0, 0, 0], 
    "is532nm": [0, 1, 0, 1, 0, 0, 0, 0], 
    "is355nm": [1, 0, 0, 0, 0, 0, 0, 0],
    "is1064nm": [0, 0, 0, 0, 0, 1, 0, 0],
    "isTot": [1, 0, 0, 1, 0, 1, 0, 0],
    "isCross": [0, 1, 0, 0, 0, 0, 0, 0],
    "is387nm": [0, 0, 1, 0, 0, 0, 0, 0],
    "is407nm": [0, 0, 0, 0, 0, 0, 1, 0],
    "is607nm": [0, 0, 0, 0, 1, 0, 0, 0],
    "channelTag": ["FR-total-355 nm", "FR-cross-532 nm", "FR-387 nm", "FR-total-532 nm", "FR-607 nm", "FR-total-1064 nm", "FR-407 nm", "unknown"],
    "minPC_fog": 60,
    "TR": [0.88, 231, 1.07, 1.37, 1.04, 1.07, 1.09, 1],
    "maxSigSlope4FilterCloud": 3e5,
    "saturate_thresh": 100,
    "heightFullOverlap": [1500, 1500, 1500, 1500, 1500, 1500, 1500, 1500],
    "minSNR_4_sigNorm": [10],
    "intNProfiles": 120,
    "minIntNProfiles": 80,
    "meteorDataSource": "gdas1",
    "radiosondeSitenum": 59287,
    "IWV_instrument": "AERONET",
    "maxIWVTLag": 0.0833,
    "minDecomLogDist355": 0.2,
    "minDecomLogDist532": 0.2,
    "minDecomLogDist1064": 0.2,
    "maxDecomHeight355": 10000,
    "maxDecomHeight532": 10000,
    "maxDecomHeight1064": 10000,
    "maxDecomThickness355": 2000,
    "maxDecomThickness532": 2000,
    "maxDecomThickness1064": 2000,
    "decomSmoothWin355": 40,
    "decomSmoothWin532": 40,
    "decomSmoothWin1064": 120,
    "minRefThickness355": 1000,
    "minRefThickness532": 1000,
    "minRefThickness1064": 1000,
    "minRefDeltaExt355": 1,
    "minRefDeltaExt532": 1,
    "minRefDeltaExt1064": 1,
    "minRefSNR355": 2,
    "minRefSNR532": 2,
    "minRefSNR1064": 2,
    "LR355": 50,
    "LR532": 50,
    "LR1064": 50,
    "refBeta355": 1e-8,
    "refBeta532": 1e-8,
    "refBeta1064": 1e-8,
    "smoothWin_klett_355": 3,
    "smoothWin_klett_532": 3,
    "smoothWin_klett_1064": 3,
    "maxIterConstrainFernald": 20,
    "minLRConstrainFernald": 1,
    "maxLRConstrainFernald": 150,
    "minDeltaAOD": 0.01,
    "minRamanRefSNR355": 50,
    "minRamanRefSNR532": 20,
    "minRamanRefSNR1064": 10,
    "minRamanRefSNR387": 50,
    "minRamanRefSNR607": 20,
    "angstrexp": 0.9,
    "smoothWin_raman_355": 25,
    "smoothWin_raman_532": 25,
    "smoothWin_raman_1064": 25,
    "LCMeanWindow": 50,
    "LCMeanMinIndx": 70,
    "LCMeanMaxIndx": 1000,
    "LCCalibrationStatus": ["none", "Klett", "Raman", "Defaults", "History"],
    "quasi_smooth_h": [2, 2, 2, 2, 2, 2, 2, 2, 2, 2, 2, 2, 2],
    "quasi_smooth_t": [10, 10, 10, 10, 10, 10, 10, 10, 10, 10, 10, 10, 10],
    "hWVCaliBase": 120,
    "hWVCaliTop": 6000,
    "minSNRWVCali": 10,

    "clear_thres_par_beta_1064": 1e-8,
    "turbid_thres_par_beta_1064": 2e-7,
    "turbid_thres_par_beta_532": 2e-7,
    "droplet_thres_par_depol": 0.05,
    "spheroid_thres_par_depol": 0.07,
    "unspheroid_thres_par_depol": 0.2,
    "ice_thres_par_depol": 0.35,
    "ice_thres_vol_depol": 0.3,
    "large_thres_ang": 0.75,
    "small_thres_ang": 0.5,
    "cloud_thres_par_beta_1064": 2e-5,
    "min_atten_par_beta_1064": 10,
    "search_cloud_above": 300,
    "search_cloud_below": 100,

    "overlap532Color": [0, 255, 64],
    "overlap355Color": [0, 0, 255],
    "xLim_Profi_RCS": [0.3, 10],
    "xLim_Profi_Bsc": [-0.1, 3],
    "xLim_Profi_Ext": [-1, 160],
    "xLim_Profi_LR": [0, 120],
    "yLim_FR_RCS": [0, 20000],
    "yLim_NR_RCS": [0, 3000],
    "xLim_Profi_WV_RH": [0, 12],
    "yLim_LC_355": [0, 1e14],
    "yLim_LC_532": [0, 2e14],
    "yLim_LC_1064": [0, 6e14],
    "yLim_LC_387": [0, 1e14],
    "yLim_LC_607": [0, 3e14],
    "yLim_WVConst": [0, 20],
    "zLim_att_beta_355": [0, 15],
    "zLim_att_beta_532": [0, 5],
    "zLim_att_beta_1064": [0, 2],
    "zLim_quasi_beta_355": [0, 8],
    "zLim_quasi_beta_532": [0, 5],
    "zLim_quasi_beta_1064": [0, 2],
    "zLim_quasi_Par_DR_532": [0, 0.4],
    "zLim_FR_RCS_355": [0, 1.5],
    "zLim_FR_RCS_532": [0, 2],
    "zLim_FR_RCS_1064": [0, 2],
    "zLim_NR_RCS_355": [0, 1.5],
    "zLim_NR_RCS_532": [0, 2],

    "calibrationDB": "pollyxt_ift_calibration.db",
    "logbookFile": "/data/level0/polly/pollyxt_ift/logbook_pollyift.csv"
}
